pqcow_liboqs-0.10.1.dev0.dist-info/top_level.txt
pqcow_liboqs-0.10.1.dev0.dist-info/RECORD
pqcow_liboqs-0.10.1.dev0.dist-info/LICENSE
pqcow_liboqs-0.10.1.dev0.dist-info/METADATA
pqcow_liboqs-0.10.1.dev0.dist-info/WHEEL
oqs/liboqs.so
oqs/oqs.py
oqs/__init__.py
oqs/rand.py
