Metadata-Version: 2.1
Name: pqcow-liboqs
Version: 0.10.1.dev0
Summary: [Compiled liboqs inside] Python bindings for liboqs, providing post-quantum public key cryptography algorithms
Author-email: Open Quantum Safe project <contact@openquantumsafe.org>
License: MIT License
Project-URL: homepage, https://github.com/open-quantum-safe/liboqs-python
Project-URL: repository, https://github.com/open-quantum-safe/liboqs-python.git
Classifier: Programming Language :: Python
Classifier: Programming Language :: Python :: 3
Classifier: Programming Language :: Python :: 3.9
Classifier: Programming Language :: Python :: 3.10
Classifier: Programming Language :: Python :: 3.11
Classifier: Programming Language :: Python :: 3.12
Classifier: Programming Language :: Python :: 3.13
Classifier: Programming Language :: Python :: 3 :: Only
Classifier: Programming Language :: Python :: Implementation :: CPython
Classifier: Typing :: Typed
Classifier: Operating System :: Microsoft :: Windows
Classifier: Operating System :: POSIX
Classifier: Operating System :: Unix
Classifier: License :: OSI Approved :: MIT License
Requires-Python: >=3.9
License-File: LICENSE
Provides-Extra: dev
Requires-Dist: isort ==5.13.2 ; extra == 'dev'
Requires-Dist: pre-commit ==4.0.1 ; extra == 'dev'
Requires-Dist: ruff ==0.7.4 ; extra == 'dev'
Requires-Dist: bandit ==1.7.10 ; extra == 'dev'
Requires-Dist: nose2 ==0.15.1 ; extra == 'dev'
Requires-Dist: setuptools ==75.5.0 ; extra == 'dev'
Provides-Extra: lint
Requires-Dist: mypy ==1.13.0 ; extra == 'lint'
Requires-Dist: types-pytz ==2024.2.0.20241003 ; extra == 'lint'
